README.md
setup.py
deribit_v2_client.egg-info/PKG-INFO
deribit_v2_client.egg-info/SOURCES.txt
deribit_v2_client.egg-info/dependency_links.txt
deribit_v2_client.egg-info/requires.txt
deribit_v2_client.egg-info/top_level.txt
openapi_client/__init__.py
openapi_client/api_client.py
openapi_client/configuration.py
openapi_client/exceptions.py
openapi_client/rest.py
openapi_client/api/__init__.py
openapi_client/api/account_management_api.py
openapi_client/api/authentication_api.py
openapi_client/api/internal_api.py
openapi_client/api/market_data_api.py
openapi_client/api/private_api.py
openapi_client/api/public_api.py
openapi_client/api/supporting_api.py
openapi_client/api/trading_api.py
openapi_client/api/wallet_api.py
openapi_client/models/__init__.py
openapi_client/models/address_book_item.py
openapi_client/models/book_summary.py
openapi_client/models/currency.py
openapi_client/models/currency_portfolio.py
openapi_client/models/currency_withdrawal_priorities.py
openapi_client/models/deposit.py
openapi_client/models/instrument.py
openapi_client/models/key_number_pair.py
openapi_client/models/order.py
openapi_client/models/order_id_initial_margin_pair.py
openapi_client/models/portfolio.py
openapi_client/models/portfolio_eth.py
openapi_client/models/position.py
openapi_client/models/public_trade.py
openapi_client/models/settlement.py
openapi_client/models/trades_volumes.py
openapi_client/models/transfer_item.py
openapi_client/models/types.py
openapi_client/models/user_trade.py
openapi_client/models/withdrawal.py
test/__init__.py
test/test_account_management_api.py
test/test_address_book_item.py
test/test_authentication_api.py
test/test_book_summary.py
test/test_currency.py
test/test_currency_portfolio.py
test/test_currency_withdrawal_priorities.py
test/test_deposit.py
test/test_instrument.py
test/test_internal_api.py
test/test_key_number_pair.py
test/test_market_data_api.py
test/test_order.py
test/test_order_id_initial_margin_pair.py
test/test_portfolio.py
test/test_portfolio_eth.py
test/test_position.py
test/test_private_api.py
test/test_public_api.py
test/test_public_trade.py
test/test_settlement.py
test/test_supporting_api.py
test/test_trades_volumes.py
