Metadata-Version: 1.0
Name: deribit-v2-client
Version: 0.0.1
Summary: Deribit API
Home-page: UNKNOWN
Author: UNKNOWN
Author-email: UNKNOWN
License: UNKNOWN
Keywords: OpenAPI,OpenAPI-Generator,Deribit API
Platform: UNKNOWN
